[
  {
    "nm_id": 100001,
    "name": "Смартфон Helios X200",
    "vendor": "Helios",
    "vendor_code": "HX200",
    "brand": "Helios",
    "category": "Электроника",
    "subject": "Смартфоны",
    "price": 18990.00,
    "discount": 15,
    "price_with_discount": 16141.50,
    "sale_price": 15990.00,
    "sale": 20,
    "basic_sale": 10,
    "basic_price_u": 18990.00,
    "total_quantity": 75,
    "quantity_not_in_orders": 50,
    "quantity_full": 120,
    "in_way_to_client": 5,
    "in_way_from_client": 2,
    "colors": "Черный",
    "sizes": "128GB"
  },
  {
    "nm_id": 100002,
    "name": "Беспроводные наушники WavePods",
    "vendor": "Wave",
    "vendor_code": "WAVE-AIR",
    "brand": "Wave",
    "category": "Электроника",
    "subject": "Наушники",
    "price": 6990.00,
    "discount": 10,
    "price_with_discount": 6291.00,
    "sale_price": 6490.00,
    "sale": 12,
    "basic_sale": 5,
    "basic_price_u": 6990.00,
    "total_quantity": 150,
    "quantity_not_in_orders": 90,
    "quantity_full": 180,
    "in_way_to_client": 12,
    "in_way_from_client": 3,
    "colors": "Белый",
    "sizes": "One Size"
  },
  {
    "nm_id": 100003,
    "name": "Рюкзак Explorer 35L",
    "vendor": "NordHike",
    "vendor_code": "NH-EXP-35",
    "brand": "NordHike",
    "category": "Спорт",
    "subject": "Рюкзаки",
    "price": 5490.00,
    "discount": 25,
    "price_with_discount": 4117.50,
    "sale_price": 4290.00,
    "sale": 22,
    "basic_sale": 8,
    "basic_price_u": 5490.00,
    "total_quantity": 40,
    "quantity_not_in_orders": 15,
    "quantity_full": 50,
    "in_way_to_client": 4,
    "in_way_from_client": 1,
    "colors": "Серый",
    "sizes": "35L"
  },
  {
    "nm_id": 100004,
    "name": "Умные часы PulseGo",
    "vendor": "Pulse",
    "vendor_code": "PULSE-GO",
    "brand": "Pulse",
    "category": "Электроника",
    "subject": "Умные часы",
    "price": 14990.00,
    "discount": 18,
    "price_with_discount": 12291.80,
    "sale_price": 11990.00,
    "sale": 15,
    "basic_sale": 7,
    "basic_price_u": 14990.00,
    "total_quantity": 95,
    "quantity_not_in_orders": 60,
    "quantity_full": 140,
    "in_way_to_client": 6,
    "in_way_from_client": 2,
    "colors": "Серый",
    "sizes": "42mm"
  },
  {
    "nm_id": 100005,
    "name": "Погружной блендер KitchenPro 900",
    "vendor": "KitchenPro",
    "vendor_code": "KP-900",
    "brand": "KitchenPro",
    "category": "Бытовая техника",
    "subject": "Блендеры",
    "price": 5790.00,
    "discount": 12,
    "price_with_discount": 5095.20,
    "sale_price": 4990.00,
    "sale": 18,
    "basic_sale": 6,
    "basic_price_u": 5790.00,
    "total_quantity": 70,
    "quantity_not_in_orders": 40,
    "quantity_full": 95,
    "in_way_to_client": 3,
    "in_way_from_client": 1,
    "colors": "Белый",
    "sizes": "900W"
  },
  {
    "nm_id": 100006,
    "name": "Термокружка ArcticCup",
    "vendor": "Arctic",
    "vendor_code": "AC-500",
    "brand": "Arctic",
    "category": "Дом и дача",
    "subject": "Термокружки",
    "price": 1590.00,
    "discount": 20,
    "price_with_discount": 1272.00,
    "sale_price": 1290.00,
    "sale": 25,
    "basic_sale": 10,
    "basic_price_u": 1590.00,
    "total_quantity": 110,
    "quantity_not_in_orders": 70,
    "quantity_full": 130,
    "in_way_to_client": 4,
    "in_way_from_client": 2,
    "colors": "Графит",
    "sizes": "500мл"
  },
  {
    "nm_id": 100007,
    "name": "Кроссовки Sprint Pro",
    "vendor": "FastRun",
    "vendor_code": "FR-SPRINT",
    "brand": "FastRun",
    "category": "Спорт",
    "subject": "Кроссовки",
    "price": 7490.00,
    "discount": 17,
    "price_with_discount": 6216.70,
    "sale_price": 6290.00,
    "sale": 20,
    "basic_sale": 9,
    "basic_price_u": 7490.00,
    "total_quantity": 160,
    "quantity_not_in_orders": 100,
    "quantity_full": 200,
    "in_way_to_client": 8,
    "in_way_from_client": 4,
    "colors": "Черный",
    "sizes": "41-45"
  },
  {
    "nm_id": 18696144301,
    "name": "Чехол для рыболовного подсака 80×85 см чёрный (логистика 29891778)",
    "vendor": "FISHING BAND",
    "vendor_code": "ch5_bl-logistics-35048275687",
    "brand": "FISHING BAND",
    "category": "Другие принадлежности для рыбалки",
    "subject": "Другие принадлежности для рыбалки",
    "price": 76.00,
    "discount": 0,
    "price_with_discount": 76.00,
    "sale_price": 76.00,
    "sale": 0,
    "basic_sale": 0,
    "basic_price_u": 76.00,
    "total_quantity": 0,
    "quantity_not_in_orders": 0,
    "quantity_full": 0,
    "in_way_to_client": 0,
    "in_way_from_client": 0,
    "colors": "чёрный",
    "sizes": "80×85 см"
  },
  {
    "nm_id": 186961443,
    "name": "Чехол для рыболовного подсака 80×85 см чёрный",
    "vendor": "FISHING BAND",
    "vendor_code": "ch5_bl",
    "brand": "FISHING BAND",
    "category": "Другие принадлежности для рыбалки",
    "subject": "Другие принадлежности для рыбалки",
    "price": 2059.55,
    "discount": 18,
    "price_with_discount": 1692.26,
    "sale_price": 1692.26,
    "sale": 18,
    "basic_sale": 0,
    "basic_price_u": 2059.55,
    "total_quantity": 1,
    "quantity_not_in_orders": 0,
    "quantity_full": 1,
    "in_way_to_client": 0,
    "in_way_from_client": 0,
    "colors": "чёрный",
    "sizes": "80×85 см"
  },
  {
    "nm_id": 18696143601,
    "name": "Чехол для подсака и подсачека непромокаемый 80×85 см хаки (логистика 40952760739)",
    "vendor": "FISHING BAND",
    "vendor_code": "ch1-logistics-40952760739",
    "brand": "FISHING BAND",
    "category": "Другие принадлежности для рыбалки",
    "subject": "Другие принадлежности для рыбалки",
    "price": 97.29,
    "discount": 0,
    "price_with_discount": 97.29,
    "sale_price": 97.29,
    "sale": 0,
    "basic_sale": 0,
    "basic_price_u": 97.29,
    "total_quantity": 0,
    "quantity_not_in_orders": 0,
    "quantity_full": 0,
    "in_way_to_client": 0,
    "in_way_from_client": 0,
    "colors": "хаки",
    "sizes": "80×85 см"
  },
  {
    "nm_id": 186961436,
    "name": "Чехол для подсака и подсачека непромокаемый 80×85 см хаки",
    "vendor": "FISHING BAND",
    "vendor_code": "ch1",
    "brand": "FISHING BAND",
    "category": "Другие принадлежности для рыбалки",
    "subject": "Другие принадлежности для рыбалки",
    "price": 1885.10,
    "discount": 0,
    "price_with_discount": 1885.10,
    "sale_price": 1885.10,
    "sale": 0,
    "basic_sale": 0,
    "basic_price_u": 1885.10,
    "total_quantity": 1,
    "quantity_not_in_orders": 0,
    "quantity_full": 1,
    "in_way_to_client": 0,
    "in_way_from_client": 0,
    "colors": "хаки",
    "sizes": "80×85 см"
  },
  {
    "nm_id": 32175750801,
    "name": "Оснастка карповая Fishing Band флэт-метод 80 г №6 (логистика 41099361170)",
    "vendor": "FISHING BAND",
    "vendor_code": "0409-logistics-41099361170",
    "brand": "FISHING BAND",
    "category": "Кормушки рыболовные",
    "subject": "Кормушки рыболовные",
    "price": 60.80,
    "discount": 0,
    "price_with_discount": 60.80,
    "sale_price": 60.80,
    "sale": 0,
    "basic_sale": 0,
    "basic_price_u": 60.80,
    "total_quantity": 0,
    "quantity_not_in_orders": 0,
    "quantity_full": 0,
    "in_way_to_client": 0,
    "in_way_from_client": 0,
    "colors": "графитовый",
    "sizes": "80 г, №6"
  },
  {
    "nm_id": 321757508,
    "name": "Оснастка карповая Fishing Band флэт-метод 80 г №6",
    "vendor": "FISHING BAND",
    "vendor_code": "0409",
    "brand": "FISHING BAND",
    "category": "Кормушки рыболовные",
    "subject": "Кормушки рыболовные",
    "price": 679.95,
    "discount": 33,
    "price_with_discount": 453.12,
    "sale_price": 453.12,
    "sale": 33,
    "basic_sale": 0,
    "basic_price_u": 679.95,
    "total_quantity": 1,
    "quantity_not_in_orders": 0,
    "quantity_full": 1,
    "in_way_to_client": 0,
    "in_way_from_client": 0,
    "colors": "тёмно-зелёный",
    "sizes": "80 г, №6"
  },
  {
    "nm_id": 32175750802,
    "name": "Оснастка карповая Fishing Band флэт-метод 80 г №6 (логистика 41107790736)",
    "vendor": "FISHING BAND",
    "vendor_code": "0409-logistics-41107790736",
    "brand": "FISHING BAND",
    "category": "Кормушки рыболовные",
    "subject": "Кормушки рыболовные",
    "price": 60.80,
    "discount": 0,
    "price_with_discount": 60.80,
    "sale_price": 60.80,
    "sale": 0,
    "basic_sale": 0,
    "basic_price_u": 60.80,
    "total_quantity": 0,
    "quantity_not_in_orders": 0,
    "quantity_full": 0,
    "in_way_to_client": 0,
    "in_way_from_client": 0,
    "colors": "тёмно-зелёный",
    "sizes": "80 г, №6"
  },
  {
    "nm_id": 32175750812,
    "name": "Оснастка карповая Fishing Band флэт-метод 80 г №6",
    "vendor": "FISHING BAND",
    "vendor_code": "0409-41107790736",
    "brand": "FISHING BAND",
    "category": "Кормушки рыболовные",
    "subject": "Кормушки рыболовные",
    "price": 679.95,
    "discount": 33,
    "price_with_discount": 453.12,
    "sale_price": 453.12,
    "sale": 33,
    "basic_sale": 0,
    "basic_price_u": 679.95,
    "total_quantity": 1,
    "quantity_not_in_orders": 0,
    "quantity_full": 1,
    "in_way_to_client": 0,
    "in_way_from_client": 0,
    "colors": "тёмно-зелёный",
    "sizes": "80 г, №6"
  },
  {
    "nm_id": 50010010101,
    "name": "Удочка RiverMaster Tele 2.4 м (логистика 29891779)",
    "vendor": "RiverMaster",
    "vendor_code": "rm_t240-logistics-29891779",
    "brand": "RiverMaster",
    "category": "Удочки",
    "subject": "Удочки",
    "price": 45.00,
    "discount": 0,
    "price_with_discount": 45.00,
    "sale_price": 45.00,
    "sale": 0,
    "basic_sale": 0,
    "basic_price_u": 45.00,
    "total_quantity": 0,
    "quantity_not_in_orders": 0,
    "quantity_full": 0,
    "in_way_to_client": 0,
    "in_way_from_client": 0,
    "colors": "чёрный",
    "sizes": "2.4 м"
  },
  {
    "nm_id": 500100101,
    "name": "Удочка RiverMaster Tele 2.4 м",
    "vendor": "RiverMaster",
    "vendor_code": "rm_t240",
    "brand": "RiverMaster",
    "category": "Удочки",
    "subject": "Удочки",
    "price": 2690.00,
    "discount": 10,
    "price_with_discount": 2421.00,
    "sale_price": 2421.00,
    "sale": 10,
    "basic_sale": 0,
    "basic_price_u": 2690.00,
    "total_quantity": 12,
    "quantity_not_in_orders": 5,
    "quantity_full": 15,
    "in_way_to_client": 2,
    "in_way_from_client": 1,
    "colors": "чёрный",
    "sizes": "2.4 м"
  },
  {
    "nm_id": 50010010201,
    "name": "Удочка RiverMaster Tele 3.0 м (логистика 29891780)",
    "vendor": "RiverMaster",
    "vendor_code": "rm_t300-logistics-29891780",
    "brand": "RiverMaster",
    "category": "Удочки",
    "subject": "Удочки",
    "price": 48.00,
    "discount": 0,
    "price_with_discount": 48.00,
    "sale_price": 48.00,
    "sale": 0,
    "basic_sale": 0,
    "basic_price_u": 48.00,
    "total_quantity": 0,
    "quantity_not_in_orders": 0,
    "quantity_full": 0,
    "in_way_to_client": 0,
    "in_way_from_client": 0,
    "colors": "чёрный",
    "sizes": "3.0 м"
  },
  {
    "nm_id": 500100102,
    "name": "Удочка RiverMaster Tele 3.0 м",
    "vendor": "RiverMaster",
    "vendor_code": "rm_t300",
    "brand": "RiverMaster",
    "category": "Удочки",
    "subject": "Удочки",
    "price": 2990.00,
    "discount": 12,
    "price_with_discount": 2631.20,
    "sale_price": 2631.20,
    "sale": 12,
    "basic_sale": 0,
    "basic_price_u": 2990.00,
    "total_quantity": 10,
    "quantity_not_in_orders": 4,
    "quantity_full": 12,
    "in_way_to_client": 1,
    "in_way_from_client": 1,
    "colors": "чёрный",
    "sizes": "3.0 м"
  },
  {
    "nm_id": 50010010301,
    "name": "Удочка IcePro Winter 60 см (логистика 29891781)",
    "vendor": "IcePro",
    "vendor_code": "ip_w60-logistics-29891781",
    "brand": "IcePro",
    "category": "Удочки",
    "subject": "Удочки",
    "price": 35.00,
    "discount": 0,
    "price_with_discount": 35.00,
    "sale_price": 35.00,
    "sale": 0,
    "basic_sale": 0,
    "basic_price_u": 35.00,
    "total_quantity": 0,
    "quantity_not_in_orders": 0,
    "quantity_full": 0,
    "in_way_to_client": 0,
    "in_way_from_client": 0,
    "colors": "синий",
    "sizes": "60 см"
  },
  {
    "nm_id": 500100103,
    "name": "Удочка IcePro Winter 60 см",
    "vendor": "IcePro",
    "vendor_code": "ip_w60",
    "brand": "IcePro",
    "category": "Удочки",
    "subject": "Удочки",
    "price": 1590.00,
    "discount": 15,
    "price_with_discount": 1351.50,
    "sale_price": 1351.50,
    "sale": 15,
    "basic_sale": 0,
    "basic_price_u": 1590.00,
    "total_quantity": 18,
    "quantity_not_in_orders": 6,
    "quantity_full": 22,
    "in_way_to_client": 2,
    "in_way_from_client": 1,
    "colors": "синий",
    "sizes": "60 см"
  },
  {
    "nm_id": 50010010401,
    "name": "Удочка IcePro Winter 80 см (логистика 29891782)",
    "vendor": "IcePro",
    "vendor_code": "ip_w80-logistics-29891782",
    "brand": "IcePro",
    "category": "Удочки",
    "subject": "Удочки",
    "price": 37.00,
    "discount": 0,
    "price_with_discount": 37.00,
    "sale_price": 37.00,
    "sale": 0,
    "basic_sale": 0,
    "basic_price_u": 37.00,
    "total_quantity": 0,
    "quantity_not_in_orders": 0,
    "quantity_full": 0,
    "in_way_to_client": 0,
    "in_way_from_client": 0,
    "colors": "красный",
    "sizes": "80 см"
  },
  {
    "nm_id": 500100104,
    "name": "Удочка IcePro Winter 80 см",
    "vendor": "IcePro",
    "vendor_code": "ip_w80",
    "brand": "IcePro",
    "category": "Удочки",
    "subject": "Удочки",
    "price": 1890.00,
    "discount": 15,
    "price_with_discount": 1606.50,
    "sale_price": 1606.50,
    "sale": 15,
    "basic_sale": 0,
    "basic_price_u": 1890.00,
    "total_quantity": 16,
    "quantity_not_in_orders": 5,
    "quantity_full": 20,
    "in_way_to_client": 2,
    "in_way_from_client": 1,
    "colors": "красный",
    "sizes": "80 см"
  },
  {
    "nm_id": 50010010501,
    "name": "Удочка StreamLine Feeder 3.3 м (логистика 29891783)",
    "vendor": "StreamLine",
    "vendor_code": "sl_f330-logistics-29891783",
    "brand": "StreamLine",
    "category": "Удочки",
    "subject": "Удочки",
    "price": 55.00,
    "discount": 0,
    "price_with_discount": 55.00,
    "sale_price": 55.00,
    "sale": 0,
    "basic_sale": 0,
    "basic_price_u": 55.00,
    "total_quantity": 0,
    "quantity_not_in_orders": 0,
    "quantity_full": 0,
    "in_way_to_client": 0,
    "in_way_from_client": 0,
    "colors": "оливковый",
    "sizes": "3.3 м"
  },
  {
    "nm_id": 500100105,
    "name": "Удочка StreamLine Feeder 3.3 м",
    "vendor": "StreamLine",
    "vendor_code": "sl_f330",
    "brand": "StreamLine",
    "category": "Удочки",
    "subject": "Удочки",
    "price": 3490.00,
    "discount": 18,
    "price_with_discount": 2861.80,
    "sale_price": 2861.80,
    "sale": 18,
    "basic_sale": 0,
    "basic_price_u": 3490.00,
    "total_quantity": 14,
    "quantity_not_in_orders": 6,
    "quantity_full": 18,
    "in_way_to_client": 2,
    "in_way_from_client": 1,
    "colors": "оливковый",
    "sizes": "3.3 м"
  },
  {
    "nm_id": 50010010601,
    "name": "Удочка StreamLine Feeder 3.6 м (логистика 29891784)",
    "vendor": "StreamLine",
    "vendor_code": "sl_f360-logistics-29891784",
    "brand": "StreamLine",
    "category": "Удочки",
    "subject": "Удочки",
    "price": 57.00,
    "discount": 0,
    "price_with_discount": 57.00,
    "sale_price": 57.00,
    "sale": 0,
    "basic_sale": 0,
    "basic_price_u": 57.00,
    "total_quantity": 0,
    "quantity_not_in_orders": 0,
    "quantity_full": 0,
    "in_way_to_client": 0,
    "in_way_from_client": 0,
    "colors": "оливковый",
    "sizes": "3.6 м"
  },
  {
    "nm_id": 500100106,
    "name": "Удочка StreamLine Feeder 3.6 м",
    "vendor": "StreamLine",
    "vendor_code": "sl_f360",
    "brand": "StreamLine",
    "category": "Удочки",
    "subject": "Удочки",
    "price": 3690.00,
    "discount": 18,
    "price_with_discount": 3025.80,
    "sale_price": 3025.80,
    "sale": 18,
    "basic_sale": 0,
    "basic_price_u": 3690.00,
    "total_quantity": 13,
    "quantity_not_in_orders": 5,
    "quantity_full": 17,
    "in_way_to_client": 2,
    "in_way_from_client": 1,
    "colors": "оливковый",
    "sizes": "3.6 м"
  },
  {
    "nm_id": 50010010701,
    "name": "Удочка AquaSpin Carbon 2.1 м (логистика 29891785)",
    "vendor": "AquaSpin",
    "vendor_code": "as_c210-logistics-29891785",
    "brand": "AquaSpin",
    "category": "Удочки",
    "subject": "Удочки",
    "price": 43.00,
    "discount": 0,
    "price_with_discount": 43.00,
    "sale_price": 43.00,
    "sale": 0,
    "basic_sale": 0,
    "basic_price_u": 43.00,
    "total_quantity": 0,
    "quantity_not_in_orders": 0,
    "quantity_full": 0,
    "in_way_to_client": 0,
    "in_way_from_client": 0,
    "colors": "графитовый",
    "sizes": "2.1 м"
  },
  {
    "nm_id": 500100107,
    "name": "Удочка AquaSpin Carbon 2.1 м",
    "vendor": "AquaSpin",
    "vendor_code": "as_c210",
    "brand": "AquaSpin",
    "category": "Удочки",
    "subject": "Удочки",
    "price": 2290.00,
    "discount": 20,
    "price_with_discount": 1832.00,
    "sale_price": 1832.00,
    "sale": 20,
    "basic_sale": 0,
    "basic_price_u": 2290.00,
    "total_quantity": 20,
    "quantity_not_in_orders": 8,
    "quantity_full": 24,
    "in_way_to_client": 3,
    "in_way_from_client": 1,
    "colors": "графитовый",
    "sizes": "2.1 м"
  },
  {
    "nm_id": 50010010801,
    "name": "Удочка AquaSpin Carbon 2.4 м (логистика 29891786)",
    "vendor": "AquaSpin",
    "vendor_code": "as_c240-logistics-29891786",
    "brand": "AquaSpin",
    "category": "Удочки",
    "subject": "Удочки",
    "price": 45.00,
    "discount": 0,
    "price_with_discount": 45.00,
    "sale_price": 45.00,
    "sale": 0,
    "basic_sale": 0,
    "basic_price_u": 45.00,
    "total_quantity": 0,
    "quantity_not_in_orders": 0,
    "quantity_full": 0,
    "in_way_to_client": 0,
    "in_way_from_client": 0,
    "colors": "графитовый",
    "sizes": "2.4 м"
  },
  {
    "nm_id": 500100108,
    "name": "Удочка AquaSpin Carbon 2.4 м",
    "vendor": "AquaSpin",
    "vendor_code": "as_c240",
    "brand": "AquaSpin",
    "category": "Удочки",
    "subject": "Удочки",
    "price": 2490.00,
    "discount": 20,
    "price_with_discount": 1992.00,
    "sale_price": 1992.00,
    "sale": 20,
    "basic_sale": 0,
    "basic_price_u": 2490.00,
    "total_quantity": 18,
    "quantity_not_in_orders": 7,
    "quantity_full": 22,
    "in_way_to_client": 3,
    "in_way_from_client": 1,
    "colors": "графитовый",
    "sizes": "2.4 м"
  }
]
